Metadata-Version: 1.1
Name: dash-easy-sort
Version: 0.0.2
Summary: Dash component for react easy sort lists.
Home-page: UNKNOWN
Author: Jim Parr <jimparr19@gmail.com>
Author-email: UNKNOWN
License: MIT
Platform: UNKNOWN
Classifier: Framework :: Dash
